rssbot/brokers.py
rssbot/clients.py
rssbot/command.py
rssbot/configs.py
rssbot/defines.py
rssbot/handler.py
rssbot/loggers.py
rssbot/message.py
rssbot/methods.py
rssbot/objects.py
rssbot/persist.py
rssbot/repeats.py
rssbot/serials.py
rssbot/statics.py
rssbot/threads.py
rssbot/timings.py
rssbot/utility.py
rssbot/workdir.py
rssbot/modules/__init__.py
rssbot/modules/atr.py
rssbot/modules/flt.py
rssbot/modules/fnd.py
rssbot/modules/irc.py
rssbot/modules/lst.py
rssbot/modules/rss.py
rssbot/modules/sil.py
rssbot/modules/thr.py
rssbot/modules/upt.py
rssbot-657.data/scripts/rssbot
rssbot-657.dist-info/METADATA
rssbot-657.dist-info/WHEEL
rssbot-657.dist-info/top_level.txt
rssbot-657.dist-info/RECORD
