Metadata-Version: 2.4
Name: rssbot
Version: 657
Summary: 24/7 IRC Feed Fetcher, a contribution back to society. Public Domain.
Author-email: Bart Thate <rssbotd@gmail.com>
License-Expression: Unlicense
Project-URL: home, https://pypi.org/project/rssbot
Project-URL: bugs, https://github.com/rssbotd/rssbot/issues
Project-URL: source, https://github.com/rssbotd/rssbot
Classifier: Development Status :: 4 - Beta
Classifier: Operating System :: Unix
Classifier: Programming Language :: Python
Classifier: Topic :: Utilities
